[{"model": "employee.profile", "pk": 1, "fields": {"user": 1, "designation": "administrator", "picture": "", "mobile": null, "icard": "", "dob": null, "doj": null, "dor": null, "prefix": "Mr.", "created": "2020-04-06T16:50:28.417", "createdby": null, "edited": "2026-02-06T20:52:29.116", "editedby": null}}, {"model": "employee.profile", "pk": 2, "fields": {"user": 2, "designation": "Director", "picture": "", "mobile": "9765643576", "icard": "", "dob": null, "doj": null, "dor": null, "prefix": "Mr.", "created": "2020-04-06T17:03:21.597", "createdby": 2, "edited": "2026-02-07T14:49:02.704", "editedby": 2}}, {"model": "employee.profile", "pk": 3, "fields": {"user": 3, "designation": "Director", "picture": "", "mobile": "7447456688", "icard": "", "dob": null, "doj": null, "dor": null, "prefix": "Mr.", "created": "2020-04-06T17:03:46.997", "createdby": null, "edited": "2026-02-07T16:28:48.526", "editedby": null}}, {"model": "employee.profile", "pk": 4, "fields": {"user": 4, "designation": "MARKETING MANAGER", "picture": "", "mobile": null, "icard": "", "dob": null, "doj": null, "dor": null, "prefix": "Mr.", "created": "2020-04-06T17:04:37.212", "createdby": null, "edited": "2022-04-07T14:21:50.192", "editedby": null}}, {"model": "employee.profile", "pk": 5, "fields": {"user": 5, "designation": "Supervisor", "picture": "", "mobile": null, "icard": "", "dob": null, "doj": null, "dor": null, "prefix": "Mr.", "created": "2020-04-06T17:09:04.320", "createdby": null, "edited": "2022-04-07T14:22:02.507", "editedby": null}}, {"model": "employee.profile", "pk": 6, "fields": {"user": 6, "designation": "", "picture": "", "mobile": null, "icard": "", "dob": null, "doj": null, "dor": null, "prefix": null, "created": "2020-05-14T14:05:06.624", "createdby": null, "edited": "2022-04-07T14:22:11.565", "editedby": null}}, {"model": "employee.profile", "pk": 7, "fields": {"user": 7, "designation": "", "picture": "", "mobile": null, "icard": "", "dob": null, "doj": null, "dor": null, "prefix": null, "created": "2020-06-20T18:09:06.810", "createdby": null, "edited": "2026-02-07T15:49:40.183", "editedby": null}}, {"model": "employee.profile", "pk": 8, "fields": {"user": 8, "designation": "Production Supervisor", "picture": "", "mobile": "9763588930", "icard": "", "dob": null, "doj": "2014-02-01", "dor": null, "prefix": "Mr.", "created": "2021-01-06T18:46:12.903", "createdby": null, "edited": "2025-05-30T13:29:12.702", "editedby": null}}, {"model": "employee.profile", "pk": 9, "fields": {"user": 9, "designation": "Marketing Executive", "picture": "", "mobile": "7447416585", "icard": "", "dob": null, "doj": null, "dor": null, "prefix": "Mr.", "created": "2021-04-17T14:36:53.577", "createdby": null, "edited": "2024-10-31T15:44:48.521", "editedby": null}}, {"model": "employee.profile", "pk": 10, "fields": {"user": 10, "designation": "", "picture": "", "mobile": null, "icard": "", "dob": null, "doj": null, "dor": null, "prefix": null, "created": "2022-01-01T16:24:41.656", "createdby": null, "edited": "2026-02-07T16:09:15.050", "editedby": null}}, {"model": "employee.profile", "pk": 11, "fields": {"user": 11, "designation": "", "picture": "", "mobile": null, "icard": "", "dob": null, "doj": null, "dor": null, "prefix": null, "created": "2022-01-01T16:25:19.642", "createdby": null, "edited": "2026-02-07T10:24:09.336", "editedby": null}}, {"model": "employee.profile", "pk": 12, "fields": {"user": 12, "designation": "", "picture": "", "mobile": null, "icard": "", "dob": null, "doj": null, "dor": null, "prefix": null, "created": "2022-01-01T16:25:56.209", "createdby": null, "edited": "2026-02-07T07:37:54.961", "editedby": null}}, {"model": "employee.profile", "pk": 13, "fields": {"user": 13, "designation": "", "picture": "", "mobile": null, "icard": "", "dob": null, "doj": null, "dor": null, "prefix": null, "created": "2022-01-01T16:26:30.906", "createdby": null, "edited": "2026-02-07T07:23:30.376", "editedby": null}}, {"model": "employee.profile", "pk": 14, "fields": {"user": 14, "designation": "", "picture": "", "mobile": null, "icard": "", "dob": null, "doj": null, "dor": null, "prefix": null, "created": "2022-01-23T16:09:12.137", "createdby": null, "edited": "2024-10-31T15:46:32.642", "editedby": null}}, {"model": "employee.profile", "pk": 15, "fields": {"user": 15, "designation": "General Manager", "picture": "", "mobile": "7447456686", "icard": "", "dob": null, "doj": null, "dor": null, "prefix": "Mr.", "created": "2022-02-28T15:06:02.977", "createdby": null, "edited": "2026-02-07T15:25:28.459", "editedby": null}}, {"model": "employee.profile", "pk": 16, "fields": {"user": 16, "designation": "Marketing Executive", "picture": "pictures/2022/06/04/WhatsApp_Image_2022-06-04_at_4.30.52_PM.jpeg", "mobile": "7709124640", "icard": "pictures/2022/06/04/WhatsApp_Image_2022-06-04_at_4.37.52_PM.jpeg", "dob": "1984-07-30", "doj": "2022-03-07", "dor": null, "prefix": "Mr.", "created": "2022-03-23T12:09:21.240", "createdby": null, "edited": "2026-02-07T16:09:57.775", "editedby": null}}, {"model": "employee.profile", "pk": 17, "fields": {"user": 17, "designation": "", "picture": "", "mobile": null, "icard": "", "dob": null, "doj": null, "dor": null, "prefix": null, "created": "2023-04-01T13:11:46.821", "createdby": null, "edited": "2024-10-31T15:45:57.206", "editedby": null}}, {"model": "employee.profile", "pk": 18, "fields": {"user": 18, "designation": "", "picture": "", "mobile": null, "icard": "", "dob": null, "doj": null, "dor": null, "prefix": null, "created": "2023-07-07T19:06:54.626", "createdby": null, "edited": "2025-12-20T11:21:36.132", "editedby": null}}, {"model": "employee.profile", "pk": 19, "fields": {"user": 19, "designation": "", "picture": "", "mobile": null, "icard": "", "dob": null, "doj": null, "dor": null, "prefix": null, "created": "2023-07-07T19:08:40.040", "createdby": null, "edited": "2024-02-19T11:57:58.778", "editedby": null}}, {"model": "employee.profile", "pk": 20, "fields": {"user": 20, "designation": "Production Manager", "picture": "", "mobile": "74478 60794", "icard": "", "dob": null, "doj": null, "dor": null, "prefix": "Mr.", "created": "2023-07-07T19:10:21.673", "createdby": null, "edited": "2025-11-26T17:44:13.603", "editedby": null}}, {"model": "employee.profile", "pk": 21, "fields": {"user": 21, "designation": "PA", "picture": "", "mobile": "9834996860", "icard": "", "dob": null, "doj": null, "dor": null, "prefix": "Mr.", "created": "2024-03-03T13:05:45.363", "createdby": null, "edited": "2025-04-10T18:01:01.146", "editedby": null}}, {"model": "employee.profile", "pk": 22, "fields": {"user": 22, "designation": "Marketing Executive", "picture": "", "mobile": "8983046794", "icard": "", "dob": null, "doj": null, "dor": null, "prefix": "Mr.", "created": "2024-03-14T10:41:42.466", "createdby": null, "edited": "2024-10-31T15:47:49.626", "editedby": null}}, {"model": "employee.profile", "pk": 23, "fields": {"user": 23, "designation": "Shift Supervisor", "picture": "", "mobile": null, "icard": "", "dob": null, "doj": null, "dor": null, "prefix": "Mr.", "created": "2024-05-13T17:02:35.135", "createdby": null, "edited": "2025-05-30T19:16:28.189", "editedby": null}}, {"model": "employee.profile", "pk": 24, "fields": {"user": 24, "designation": "Shift Supervisor", "picture": "", "mobile": null, "icard": "", "dob": null, "doj": null, "dor": null, "prefix": "Mr.", "created": "2024-05-13T17:03:12.905", "createdby": null, "edited": "2026-02-06T18:04:29.884", "editedby": null}}, {"model": "employee.profile", "pk": 25, "fields": {"user": 25, "designation": "Shift Supervisor", "picture": "", "mobile": null, "icard": "", "dob": null, "doj": null, "dor": null, "prefix": "Mr.", "created": "2024-05-13T17:03:39.663", "createdby": null, "edited": "2026-02-07T15:38:28.441", "editedby": null}}, {"model": "employee.profile", "pk": 26, "fields": {"user": 26, "designation": "Marketing Executive", "picture": "", "mobile": null, "icard": "", "dob": null, "doj": null, "dor": null, "prefix": "Mr.", "created": "2024-05-16T12:10:08.683", "createdby": null, "edited": "2026-02-06T14:01:45.657", "editedby": null}}, {"model": "employee.profile", "pk": 27, "fields": {"user": 27, "designation": "Store Manager", "picture": "", "mobile": "9022744390", "icard": "", "dob": null, "doj": null, "dor": null, "prefix": "Mr.", "created": "2024-05-23T17:18:08.308", "createdby": null, "edited": "2024-10-31T15:48:11.034", "editedby": null}}, {"model": "employee.profile", "pk": 28, "fields": {"user": 28, "designation": "CEO", "picture": "", "mobile": null, "icard": "", "dob": null, "doj": null, "dor": null, "prefix": "Mr.", "created": "2024-05-27T16:24:19.902", "createdby": null, "edited": "2024-09-04T16:12:37.764", "editedby": null}}, {"model": "employee.profile", "pk": 29, "fields": {"user": 29, "designation": "Store Manager", "picture": "", "mobile": null, "icard": "", "dob": null, "doj": null, "dor": null, "prefix": "Mr.", "created": "2024-07-27T12:04:05.446", "createdby": null, "edited": "2024-10-31T15:47:16.567", "editedby": null}}, {"model": "employee.profile", "pk": 30, "fields": {"user": 30, "designation": "Store Manager", "picture": "", "mobile": "7058798947", "icard": "", "dob": "2001-10-27", "doj": "2024-09-18", "dor": null, "prefix": "Mr.", "created": "2024-09-25T17:48:33.007", "createdby": null, "edited": "2026-02-07T16:32:59.589", "editedby": null}}, {"model": "employee.profile", "pk": 31, "fields": {"user": 31, "designation": "Accountant", "picture": "", "mobile": null, "icard": "", "dob": null, "doj": null, "dor": null, "prefix": "Ms.", "created": "2024-10-17T15:50:50.565", "createdby": null, "edited": "2026-01-11T10:29:55.839", "editedby": null}}, {"model": "employee.profile", "pk": 32, "fields": {"user": 32, "designation": "Marketing Executive", "picture": "", "mobile": "8956144990", "icard": "", "dob": null, "doj": null, "dor": null, "prefix": "Mr.", "created": "2025-01-09T12:13:12.080", "createdby": null, "edited": "2026-02-06T17:06:10.131", "editedby": null}}, {"model": "employee.profile", "pk": 33, "fields": {"user": 33, "designation": "Marketing Executive", "picture": "", "mobile": null, "icard": "", "dob": null, "doj": null, "dor": null, "prefix": "Mr.", "created": "2025-01-16T13:00:25.809", "createdby": null, "edited": "2025-04-28T12:57:15.533", "editedby": null}}, {"model": "employee.profile", "pk": 34, "fields": {"user": 34, "designation": "Design Coordinator", "picture": "", "mobile": "9763941589", "icard": "", "dob": null, "doj": null, "dor": null, "prefix": "Ms.", "created": "2025-03-19T16:44:07.959", "createdby": null, "edited": "2026-02-07T14:17:27.177", "editedby": null}}, {"model": "employee.profile", "pk": 35, "fields": {"user": 35, "designation": "Customer Coordinator", "picture": "", "mobile": "9022673350", "icard": "", "dob": "2003-04-19", "doj": "2025-03-16", "dor": null, "prefix": "Mr.", "created": "2025-03-22T11:08:53.661", "createdby": null, "edited": "2025-05-25T09:18:33.948", "editedby": null}}, {"model": "employee.profile", "pk": 36, "fields": {"user": 36, "designation": "Maintance Supervisor", "picture": "", "mobile": "8600948986", "icard": "", "dob": null, "doj": "2025-03-05", "dor": null, "prefix": "Mr.", "created": "2025-03-26T12:04:01.947", "createdby": null, "edited": "2026-02-07T13:52:04.152", "editedby": null}}, {"model": "employee.profile", "pk": 37, "fields": {"user": 37, "designation": "Design Coordinator", "picture": "", "mobile": "9856144989", "icard": "", "dob": null, "doj": null, "dor": null, "prefix": "Ms.", "created": "2025-04-14T21:27:27.837", "createdby": null, "edited": "2026-02-07T17:17:14.927", "editedby": null}}, {"model": "employee.profile", "pk": 38, "fields": {"user": 38, "designation": "", "picture": "", "mobile": null, "icard": "", "dob": null, "doj": null, "dor": null, "prefix": null, "created": "2025-04-14T21:28:30.503", "createdby": null, "edited": "2025-08-13T17:54:42.445", "editedby": null}}, {"model": "employee.profile", "pk": 39, "fields": {"user": 39, "designation": "Prodcution Planning Manager", "picture": "", "mobile": "9511772792", "icard": "", "dob": null, "doj": "2025-09-01", "dor": "2026-02-06", "prefix": "Mr.", "created": "2025-08-14T10:38:11.594", "createdby": null, "edited": "2026-02-06T16:13:20.332", "editedby": null}}, {"model": "employee.profile", "pk": 40, "fields": {"user": 40, "designation": "Marketing Executive", "picture": "", "mobile": null, "icard": "", "dob": null, "doj": null, "dor": null, "prefix": "Mr.", "created": "2025-08-27T14:45:00.052", "createdby": null, "edited": "2025-09-28T12:32:31.204", "editedby": null}}, {"model": "employee.profile", "pk": 41, "fields": {"user": 41, "designation": "Marketing Executive", "picture": "", "mobile": null, "icard": "", "dob": null, "doj": null, "dor": null, "prefix": "Mr.", "created": "2025-08-29T23:45:29.566", "createdby": null, "edited": "2026-02-07T17:11:42.484", "editedby": null}}, {"model": "employee.profile", "pk": 42, "fields": {"user": 42, "designation": "Hr Manager", "picture": "", "mobile": null, "icard": "", "dob": null, "doj": null, "dor": null, "prefix": "Mr.", "created": "2025-11-12T15:40:23.504", "createdby": null, "edited": "2026-01-24T10:34:17.933", "editedby": null}}]