[{"model": "purchase.poimage", "pk": 1, "fields": {"po": 2, "imagename": "jj", "poimage": "PoImage/A.R.EN.jpeg", "created": "2021-08-29T16:37:27.087", "createdby": 9, "edited": "2021-08-29T16:37:27.087", "editedby": null}}, {"model": "purchase.poimage", "pk": 2, "fields": {"po": 2, "imagename": "ankur", "poimage": "PoImage/WhatsApp_Image_2021-08-29_at_4.40.02_PM.jpeg", "created": "2021-08-29T16:41:36.934", "createdby": 9, "edited": "2021-08-29T16:41:36.934", "editedby": null}}, {"model": "purchase.poimage", "pk": 3, "fields": {"po": 2, "imagename": "ankur", "poimage": "PoImage/WhatsApp_Image_2021-08-29_at_4.40.03_PM.jpeg", "created": "2021-08-29T16:42:05.387", "createdby": 9, "edited": "2021-08-29T16:42:05.387", "editedby": null}}, {"model": "purchase.poimage", "pk": 4, "fields": {"po": 10, "imagename": "TEST", "poimage": "PoImage/noimage.jpg", "created": "2021-09-14T20:30:55.946", "createdby": 2, "edited": "2021-09-14T20:30:55.946", "editedby": null}}, {"model": "purchase.poimage", "pk": 5, "fields": {"po": 10, "imagename": "TEST2", "poimage": "PoImage/noimage_WrPYZfI.jpg", "created": "2021-09-14T20:31:17.038", "createdby": 2, "edited": "2021-09-14T20:31:17.038", "editedby": null}}, {"model": "purchase.poimage", "pk": 6, "fields": {"po": 21, "imagename": "DATTA KRUPA TRAVELS", "poimage": "PoImage/WhatsApp_Image_2021-09-18_at_15.47.35.jpeg", "created": "2021-09-18T15:51:28.686", "createdby": 2, "edited": "2021-09-18T15:51:28.686", "editedby": null}}, {"model": "purchase.poimage", "pk": 7, "fields": {"po": 21, "imagename": "tesing", "poimage": "PoImage/r1.jpg", "created": "2021-09-20T11:55:53.560", "createdby": 2, "edited": "2021-09-20T11:55:53.560", "editedby": null}}, {"model": "purchase.poimage", "pk": 8, "fields": {"po": 52, "imagename": "Lr Copy", "poimage": "PoImage/r1_LM7J12w.jpg", "created": "2021-09-26T13:27:54.807", "createdby": 2, "edited": "2021-09-26T13:27:54.807", "editedby": null}}, {"model": "purchase.poimage", "pk": 9, "fields": {"po": 39, "imagename": "lr copy", "poimage": "PoImage/WhatsApp_Image_2021-09-26_at_13.13.08.jpeg", "created": "2021-09-26T13:31:31.679", "createdby": 2, "edited": "2021-09-26T13:31:31.679", "editedby": null}}, {"model": "purchase.poimage", "pk": 10, "fields": {"po": 299, "imagename": "invoice", "poimage": "PoImage/WhatsApp_Image_2022-03-30_at_13.08.25.jpeg", "created": "2022-03-30T13:09:57.117", "createdby": 16, "edited": "2022-03-30T13:09:57.118", "editedby": null}}, {"model": "purchase.poimage", "pk": 11, "fields": {"po": 371, "imagename": "DC", "poimage": "PoImage/vicky_enterprises.jpeg", "created": "2022-05-16T17:08:06.727", "createdby": 16, "edited": "2022-05-16T17:08:06.727", "editedby": null}}, {"model": "purchase.poimage", "pk": 12, "fields": {"po": 371, "imagename": "INVOICE", "poimage": "PoImage/vicky_enterprises1.jpeg", "created": "2022-05-16T17:08:34.255", "createdby": 16, "edited": "2022-05-16T17:08:34.255", "editedby": null}}, {"model": "purchase.poimage", "pk": 13, "fields": {"po": 1879, "imagename": "testing", "poimage": "PoImage/MANMAR_RUDRA__MAGNESIUM.jpg", "created": "2024-07-15T19:26:43.133", "createdby": 2, "edited": "2024-07-15T19:26:43.133", "editedby": null}}, {"model": "purchase.poimage", "pk": 14, "fields": {"po": 1879, "imagename": "test2", "poimage": "PoImage/for_cylinder_VIRAJ_MANGO_SHRIKHAND_and_badam_pista_srikhand_250GM_13-07-2024-01-1.jpg", "created": "2024-07-15T19:27:10.335", "createdby": 2, "edited": "2024-07-15T19:27:10.335", "editedby": null}}, {"model": "purchase.poimage", "pk": 15, "fields": {"po": 1951, "imagename": "RUBBER WHEEL", "poimage": "PoImage/RUBBER_WHEEL.webp", "created": "2024-08-19T12:30:43.234", "createdby": 20, "edited": "2024-08-19T12:30:43.234", "editedby": null}}, {"model": "purchase.poimage", "pk": 16, "fields": {"po": 1951, "imagename": "SILICON RUBBER WHEEL", "poimage": "PoImage/RUBBER.jpg", "created": "2024-08-19T12:31:02.838", "createdby": 20, "edited": "2024-08-19T12:31:02.838", "editedby": null}}, {"model": "purchase.poimage", "pk": 17, "fields": {"po": 2385, "imagename": "abc", "poimage": "PoImage/2734-5KG_-_GOLDRANJ_ATTA_-_CENTRE_SEAL_POUCH-GOLDRANJ_NO_1_AGRO_FOOD_PRODUCTS_INDUSTRIES.png", "created": "2025-05-23T10:40:16.187", "createdby": 2, "edited": "2025-05-23T10:40:16.187", "editedby": null}}, {"model": "purchase.poimage", "pk": 18, "fields": {"po": 2385, "imagename": "hi", "poimage": "PoImage/1022-ANKUR_POLY_PACK_INDUSTRIES.png", "created": "2025-05-23T10:40:53.138", "createdby": 2, "edited": "2025-05-23T10:40:53.138", "editedby": null}}]